trifl/__init__.py
trifl/analysis.py
trifl/cli.py
trifl/config.py
trifl/dataset.py
trifl/exceptions.py
trifl/filters/__init__.py
trifl/filters/isobaric.py
trifl/filters/isotopic.py
trifl/filters/shared.py
trifl/models.py
trifl/parse/__init__.py
trifl/parse/census.py
trifl/parse/cimage.py
trifl/utils.py
trifl-0.1.6.dist-info/LICENSE
trifl-0.1.6.dist-info/WHEEL
trifl-0.1.6.dist-info/METADATA
trifl-0.1.6.dist-info/RECORD
